.gitignore
.travis.yml
LICENSE
MANIFEST.in
README.rst
setup.cfg
setup.py
tox.ini
docs/Makefile
docs/conf.py
docs/index.rst
docs/make.bat
examples/simple/.gitignore
examples/simple/app.py
examples/simple/requirements.txt
examples/simple/test_requirements.txt
examples/simple/.chalice/config.json
examples/simple/tests/__init__.py
examples/simple/tests/conftest.py
examples/simple/tests/test_app.py
pytest_chalice/__init__.py
pytest_chalice/fixtures.py
pytest_chalice/handlers.py
pytest_chalice/plugin.py
pytest_chalice.egg-info/PKG-INFO
pytest_chalice.egg-info/SOURCES.txt
pytest_chalice.egg-info/dependency_links.txt
pytest_chalice.egg-info/entry_points.txt
pytest_chalice.egg-info/requires.txt
pytest_chalice.egg-info/top_level.txt
tests/conftest.py
tests/test_chalice.py